Compiled from "JavaTest.java"
public class cn.amos.chaos.test.jvm.JavaTest {
  public cn.amos.chaos.test.jvm.JavaTest();
    Code:
       0: aload_0
       1: invokespecial #1                  // Method java/lang/Object."<init>":()V
       4: aload_0
       5: new           #2                  // class java/util/HashMap
       8: dup
       9: invokespecial #3                  // Method java/util/HashMap."<init>":()V
      12: putfield      #4                  // Field BASE_MAP:Ljava/util/Map;
      15: return

  public static void main(java.lang.String[]);
    Code:
       0: invokestatic  #5                  // Method hello:()I
       3: istore_1
       4: getstatic     #6                  // Field java/lang/System.out:Ljava/io/PrintStream;
       7: iload_1
       8: invokevirtual #7                  // Method java/io/PrintStream.println:(I)V
      11: return

  public static int hello();
    Code:
       0: new           #2                  // class java/util/HashMap
       3: dup
       4: invokespecial #3                  // Method java/util/HashMap."<init>":()V
       7: astore_0
       8: aload_0
       9: ldc           #8                  // String amos
      11: sipush        666
      14: invokestatic  #9                  // Method java/lang/Integer.valueOf:(I)Ljava/lang/Integer;
      17: invokevirtual #10                 // Method java/util/HashMap.put:(Ljava/lang/Object;Ljava/lang/Object;)Ljava/lang/Object;
      20: pop
      21: getstatic     #6                  // Field java/lang/System.out:Ljava/io/PrintStream;
      24: new           #11                 // class java/lang/StringBuilder
      27: dup
      28: invokespecial #12                 // Method java/lang/StringBuilder."<init>":()V
      31: ldc           #13                 // String hello map:
      33: invokevirtual #14                 // Method java/lang/StringBuilder.append:(Ljava/lang/String;)Ljava/lang/StringBuilder;
      36: aload_0
      37: invokevirtual #15                 // Method java/lang/StringBuilder.append:(Ljava/lang/Object;)Ljava/lang/StringBuilder;
      40: invokevirtual #16                 // Method java/lang/StringBuilder.toString:()Ljava/lang/String;
      43: invokevirtual #17                 // Method java/io/PrintStream.println:(Ljava/lang/String;)V
      46: bipush        10
      48: istore_1
      49: bipush        100
      51: istore_2
      52: new           #18                 // class java/util/Random
      55: dup
      56: invokespecial #19                 // Method java/util/Random."<init>":()V
      59: invokevirtual #20                 // Method java/util/Random.nextBoolean:()Z
      62: istore_3
      63: iload_3
      64: ifeq          74
      67: getstatic     #6                  // Field java/lang/System.out:Ljava/io/PrintStream;
      70: iload_1
      71: invokevirtual #7                  // Method java/io/PrintStream.println:(I)V
      74: iload_2
      75: iload_1
      76: iadd
      77: istore_2
      78: iload_2
      79: ireturn
}
